npfl139/LICENSE
npfl139/README.md
npfl139/__init__.py
npfl139/env_wrappers.py
npfl139/evaluation_env.py
npfl139/initializers_override.py
npfl139/monolithic_replay_buffer.py
npfl139/replay_buffer.py
npfl139/startup.py
npfl139/typed_torch_function.py
npfl139/update_params_by_ema.py
npfl139/version.py
npfl139/board_games/__init__.py
npfl139/board_games/az_quiz.py
npfl139/board_games/az_quiz_player_fork_heuristic.py
npfl139/board_games/az_quiz_player_keyboard.py
npfl139/board_games/az_quiz_player_mouse.py
npfl139/board_games/az_quiz_player_random.py
npfl139/board_games/az_quiz_player_simple_heuristic.py
npfl139/board_games/board_game.py
npfl139/board_games/board_game_evaluator.py
npfl139/board_games/board_game_player.py
npfl139/board_games/evaluate.py
npfl139/board_games/pisqorky.py
npfl139/board_games/pisqorky_player_heuristic.py
npfl139/board_games/pisqorky_player_mouse.py
npfl139/board_games/pisqorky_player_random.py
npfl139/envs/__init__.py
npfl139/envs/atari_interactive.py
npfl139/envs/car_racing.py
npfl139/envs/car_racing_interactive.py
npfl139/envs/cart_pole_pixels.py
npfl139/envs/cart_pole_pixels_interactive.py
npfl139/envs/memory_game.py
npfl139/envs/multi_collect.py
npfl139/envs/single_collect.py
npfl139/envs/single_collect_interactive.py
npfl139-2425.13.0.dist-info/licenses/npfl139/LICENSE
npfl139-2425.13.0.dist-info/METADATA
npfl139-2425.13.0.dist-info/WHEEL
npfl139-2425.13.0.dist-info/top_level.txt
npfl139-2425.13.0.dist-info/RECORD
