Metadata-Version: 2.4
Name: npfl139
Version: 2425.13.0
Summary: Modules used by the Deep Reinforcement Learning Course NPFL139
Author-email: Milan Straka <straka@ufal.mff.cuni.cz>
License: MPL-2.0
Project-URL: Homepage, https://ufal.mff.cuni.cz/courses/npfl139
Project-URL: Repository, https://github.com/ufal/npfl139
Classifier: License :: OSI Approved :: Mozilla Public License 2.0 (MPL 2.0)
Classifier: Programming Language :: Python :: 3
Requires-Python: >=3.10
License-File: npfl139/LICENSE
Requires-Dist: torch~=2.6.0
Requires-Dist: torchaudio~=2.6.0
Requires-Dist: torchvision~=0.21.0
Requires-Dist: gymnasium~=1.1.1
Requires-Dist: pygame~=2.6.1
Requires-Dist: ufal.pybox2d~=2.3.10.4
Requires-Dist: mujoco~=3.2.7
Requires-Dist: imageio~=2.37.0
Requires-Dist: ale_py~=0.10.2
Requires-Dist: pybind11~=2.13.6
Requires-Dist: matplotlib~=3.10.1
Requires-Dist: opencv-python~=4.11.0.86
Dynamic: license-file
